pyprojectx/__init__.py
pyprojectx/cli.py
pyprojectx/config.py
pyprojectx/env.py
pyprojectx/hash.py
pyprojectx/install_global.py
pyprojectx/lock.py
pyprojectx/log.py
pyprojectx/requirements.py
pyprojectx/wrapper/__init__.py
pyprojectx/wrapper/pw.bat
pyprojectx/wrapper/pw.ps1
pyprojectx/wrapper/pw.py
pyprojectx/wrapper/px
pyprojectx/wrapper/px.bat
pyprojectx/wrapper/pxg
pyprojectx/wrapper/pxg.bat
pyprojectx-3.3.2.dist-info/WHEEL
pyprojectx-3.3.2.dist-info/entry_points.txt
pyprojectx-3.3.2.dist-info/METADATA
pyprojectx-3.3.2.dist-info/RECORD
