Metadata-Version: 2.3
Name: pyprojectx
Version: 3.3.2
Summary: Execute scripts from pyproject.toml, installing tools on-the-fly
Keywords: build,dependency,pyprojectx
Author: Houbie
Author-email: Houbie <ivo@houbrechts-it.be>
License: MIT
Classifier: Topic :: Software Development :: Build Tools
Classifier: Topic :: Software Development :: Libraries :: Python Modules
Requires-Dist: click==8.1.8 ; python_full_version < '3.10'
Requires-Dist: click==8.3.1 ; python_full_version >= '3.10'
Requires-Dist: colorama==0.4.6 ; sys_platform == 'win32'
Requires-Dist: tomlkit==0.13.3
Requires-Dist: userpath==1.9.2
Requires-Dist: uv==0.9.16
Requires-Python: >=3.9
Project-URL: documentation, https://pyprojectx.github.io
Project-URL: homepage, https://github.com/pyprojectx/pyprojectx
